Workbook

Sheet Matriz_v3
A1: ID | B1: DIM | C1: INDICADOR | D1: PESO | E1: POLARIDAD | F1: METRICA | G1: NIVEL 0 | H1: NIVEL 25 | I1: NIVEL 50 | J1: NIVEL 75 | K1: NIVEL 100 | L1: FUENTE_PREF | M1: NO_DOBLE_CONTEO | N1: REGLA DE USO
A2: F01 | B2: FIN | C2: Rentabilidad operativa | D2: 14 | E2: Mayor es mejor | F2: Margen EBIT = resultado de explotación / cifra de negocio. | G2: EBIT negativo. | H2: Margen 0–3 %. | I2: Margen 3–7 %. | J2: Margen 7–11 %. | K2: Margen superior al 11 %. | L2: N1 | M2: F02, P05 | N2: Puntuar 0–100 eligiendo el nivel de la rúbrica cuya descripción se cumple con evidencia citada (EVIDENCIA_ID). Valores intermedios solo si la evidencia sitúa a la empresa entre dos niveles; conservar el rango. Sin evidencia suficiente: no puntuar. Usar EBIT reportado. Si la empresa publica un EBIT ajustado, declararlo como cálculo de la fuente y puntuar con el reportado. Equivalencias: IFRS 'operating profit'; US GAAP 'operating income'; GAAP local, verificar partida y declarar.
A3: F02 | B3: FIN | C3: Evolución de rentabilidad | D3: 8 | E3: Mayor es mejor | F3: Margen EBIT (t) − margen EBIT (t-2), perímetro homogéneo. | G3: Deterioro superior a 3 pp o paso a pérdidas. | H3: Deterioro de 1 a 3 pp. | I3: Estable, variación dentro de ±1 pp. | J3: Mejora de 1 a 3 pp. | K3: Mejora superior a 3 pp con tendencia sostenida en los tres ejercicios. | L3: N1 | M3: F01 | N3: Puntuar 0–100 eligiendo el nivel de la rúbrica cuya descripción se cumple con evidencia citada (EVIDENCIA_ID). Valores intermedios solo si la evidencia sitúa a la empresa entre dos niveles; conservar el rango. Sin evidencia suficiente: no puntuar. Si ha habido cambio de perímetro (adquisiciones, desinversiones), comparar sobre cifras reexpresadas o declarar la ruptura de serie.
A4: F03 | B4: FIN | C4: Generación de caja operativa | D4: 12 | E4: Mayor es mejor | F4: Flujo de caja operativo / EBITDA (o / EBIT si el EBITDA no está publicado), media de los dos últimos ejercicios. | G4: FCO negativo en dos de los tres últimos ejercicios. | H4: FCO negativo en el último ejercicio. | I4: FCO positivo pero inferior al 50 % del EBITDA. | J4: FCO entre el 50 % y el 90 % del EBITDA. | K4: FCO igual o superior al 90 % del EBITDA de forma sostenida. | L4: N1 | M4: F04 | N4: Puntuar 0–100 eligiendo el nivel de la rúbrica cuya descripción se cumple con evidencia citada (EVIDENCIA_ID). Valores intermedios solo si la evidencia sitúa a la empresa entre dos niveles; conservar el rango. Sin evidencia suficiente: no puntuar. Los anticipos de clientes en contratos de defensa distorsionan el FCO de un ejercicio concreto. Declarar su peso y usar la media de dos ejercicios.
A5: F04 | B5: FIN | C5: Liquidez | D5: 8 | E5: Mayor es mejor | F5: Ratio corriente (activo corriente / pasivo corriente) y cobertura de los vencimientos financieros a 12 meses con caja y líneas disponibles. | G5: Caja y líneas no cubren los vencimientos a 12 meses, o ratio corriente inferior a 0,7. | H5: Ratio corriente 0,7–0,9. | I5: Ratio corriente 0,9–1,1. | J5: Ratio corriente 1,1–1,4 y vencimientos a 12 meses cubiertos. | K5: Ratio corriente superior a 1,4 y vencimientos a 24 meses cubiertos. | L5: N1 | M5: F03, F05 | N5: Puntuar 0–100 eligiendo el nivel de la rúbrica cuya descripción se cumple con evidencia citada (EVIDENCIA_ID). Valores intermedios solo si la evidencia sitúa a la empresa entre dos niveles; conservar el rango. Sin evidencia suficiente: no puntuar. Los anticipos de clientes figuran como pasivo corriente contractual y reducen el ratio sin ser deuda exigible en efectivo. Declararlos.
A6: F05 | B6: FIN | C6: Endeudamiento financiero | D6: 10 | E6: Menor es mejor | F6: Deuda financiera neta / EBITDA. Deuda financiera = préstamos + bonos + pasivos por arrendamiento − caja y equivalentes. | G6: Superior a 4x, o EBITDA nulo o negativo con deuda. | H6: Entre 3x y 4x. | I6: Entre 2x y 3x. | J6: Entre 1x y 2x. | K6: Inferior a 1x o posición de caja neta. | L6: N1 | M6: F06, F07 | N6: Puntuar 0–100 eligiendo el nivel de la rúbrica cuya descripción se cumple con evidencia citada (EVIDENCIA_ID). Valores intermedios solo si la evidencia sitúa a la empresa entre dos niveles; conservar el rango. Sin evidencia suficiente: no puntuar. Los préstamos participativos, la deuda subordinada pública y los instrumentos híbridos se declaran por separado y no se suman a la deuda ordinaria sin indicarlo. Bajo IFRS 16 los arrendamientos son deuda; bajo US GAAP los operativos no, declarar la diferencia.
A7: F06 | B7: FIN | C7: Patrimonio y solvencia | D7: 10 | E7: Mayor es mejor | F7: Patrimonio neto / activo total y existencia de causas legales de recapitalización o disolución. | G7: Patrimonio neto negativo o causa legal de disolución o recapitalización forzosa. | H7: Patrimonio inferior al 10 % del activo. | I7: Patrimonio entre el 10 % y el 20 % del activo. | J7: Patrimonio entre el 20 % y el 35 % del activo. | K7: Patrimonio superior al 35 % del activo sin ampliaciones de rescate en los últimos cinco ejercicios. | L7: N1 | M7: F05 | N7: Puntuar 0–100 eligiendo el nivel de la rúbrica cuya descripción se cumple con evidencia citada (EVIDENCIA_ID). Valores intermedios solo si la evidencia sitúa a la empresa entre dos niveles; conservar el rango. Sin evidencia suficiente: no puntuar. Las ampliaciones de capital suscritas por el Estado para cubrir pérdidas se computan como rescate. Las suscritas para financiar inversión con plan de retorno no.
A8: F07 | B8: FIN | C8: Dependencia financiera de apoyo público | D8: 8 | E8: Menor es mejor | F8: (Subvenciones de explotación + aportaciones de capital para cubrir pérdidas + préstamos blandos o participativos + avales públicos ejecutados) / cifra de negocio, media de tres ejercicios. | G8: Superior al 20 %, o recapitalización pública recurrente para cubrir pérdidas. | H8: Entre el 10 % y el 20 %. | I8: Entre el 5 % y el 10 %. | J8: Entre el 1 % y el 5 %. | K8: Inferior al 1 %. | L8: N1 | M8: F05, F06 | N8: Puntuar 0–100 eligiendo el nivel de la rúbrica cuya descripción se cumple con evidencia citada (EVIDENCIA_ID). Valores intermedios solo si la evidencia sitúa a la empresa entre dos niveles; conservar el rango. Sin evidencia suficiente: no puntuar. Una empresa de propiedad pública sin apoyo financiero puntúa 100. Los contratos de I+D remunerados a precio de mercado no son apoyo; la prefinanciación ministerial a tipo cero o los préstamos reembolsables sin interés sí lo son. En cada jurisdicción identificar el instrumento equivalente.
A9: F08 | B9: FIN | C9: Cartera: cobertura y conversión | D9: 14 | E9: Mayor es mejor | F9: Cartera firme / cifra de negocio (años de actividad cubiertos) y ratio de conversión histórica (ingresos del ejercicio / cartera prevista a ejecutar en el ejercicio). | G9: Inferior a 0,5 años, o definición de cartera no verificable. | H9: Entre 0,5 y 1 año. | I9: Entre 1 y 2 años. | J9: Entre 2 y 3 años con conversión regular. | K9: Superior a 3 años, cartera firme con definición contractual y conversión histórica acreditada. | L9: N1 | M9: D02, P02 | N9: Puntuar 0–100 eligiendo el nivel de la rúbrica cuya descripción se cumple con evidencia citada (EVIDENCIA_ID). Valores intermedios solo si la evidencia sitúa a la empresa entre dos niveles; conservar el rango. Sin evidencia suficiente: no puntuar. Si la fuente no separa cartera firme de opciones o pipeline, la puntuación máxima es 50 y se etiqueta como ESTIMACIÓN. D02 evalúa la composición y firmeza de la cartera militar; P02 la cobertura de los ingresos previstos. Un mismo dato de cartera no puede elevar los tres.
A10: F09 | B10: FIN | C10: Disciplina de capital | D10: 8 | E10: Mayor es mejor | F10: (Capex + I+D autofinanciada + dividendos + adquisiciones) frente al flujo de caja operativo, y resultado de las adquisiciones (deterioros). | G10: Inversión y retribución financiadas con deuda creciente o apoyo público, sin retorno visible. | H10: Inversión errática o adquisiciones con deterioros relevantes. | I10: Inversión cubierta por caja pero sin priorización clara. | J10: Inversión cubierta por caja y priorizada hacia programas con contrato. | K10: Ciclo de inversión completo financiado con caja operativa y retornos demostrados. | L10: N1 | M10: I08 | N10: Puntuar 0–100 eligiendo el nivel de la rúbrica cuya descripción se cumple con evidencia citada (EVIDENCIA_ID). Valores intermedios solo si la evidencia sitúa a la empresa entre dos niveles; conservar el rango. Sin evidencia suficiente: no puntuar. I08 evalúa el volumen y destino industrial del capex; F09 evalúa su financiación y disciplina.
A11: F10 | B11: FIN | C11: Riesgo financiero extraordinario | D11: 8 | E11: Menor es mejor | F11: (Provisiones por sobrecostes de programas + litigios + garantías ejecutables + sanciones + otras contingencias materiales) / cifra de negocio. | G11: Igual o superior al 10 %, o un evento con capacidad de comprometer la continuidad. | H11: Entre el 5 % y el 10 %. | I11: Entre el 2 % y el 5 %. | J11: Inferior al 2 % con contingencias identificadas y cubiertas. | K11: Sin contingencias materiales, con opinión de auditoría sin salvedades. | L11: N1 | M11: D12, P07 | N11: Puntuar 0–100 eligiendo el nivel de la rúbrica cuya descripción se cumple con evidencia citada (EVIDENCIA_ID). Valores intermedios solo si la evidencia sitúa a la empresa entre dos niveles; conservar el rango. Sin evidencia suficiente: no puntuar. Las sanciones internacionales y las restricciones de exportación se evalúan en D10; aquí solo su efecto financiero cuantificado.
A12: I01 | B12: IND | C12: Capacidad industrial | D12: 18 | E12: Mayor es mejor | F12: Subcriterios: (a) instalaciones y equipos existentes; (b) capacidad efectivamente utilizable (certificaciones, cuellos de botella); (c) producción y entregas acreditadas en los últimos tres años; (d) capacidad disponible para nueva carga. | G12: Capacidad instalada sin producción demostrada o instalaciones obsoletas. | H12: Capacidad instalada relevante pero efectiva limitada por cuellos de botella o certificaciones pendientes. | I12: Capacidad efectiva acreditada en producto de baja complejidad o series cortas. | J12: Capacidad demostrada con entregas de programas complejos en plazo en los últimos tres años. | K12: Capacidad demostrada en varios programas complejos simultáneos y con capacidad disponible para nueva carga. | L12: N2 | M12: I02, I09 | N12: Puntuar 0–100 eligiendo el nivel de la rúbrica cuya descripción se cumple con evidencia citada (EVIDENCIA_ID). Valores intermedios solo si la evidencia sitúa a la empresa entre dos niveles; conservar el rango. Sin evidencia suficiente: no puntuar. Sustituye a los antiguos indicadores de capacidad instalada, efectiva y demostrada, que eran conceptos anidados y triplicaban el crédito.
A13: I02 | B13: IND | C13: Carga y utilización | D13: 10 | E13: Óptimo intermedio | F13: Utilización estimada de la capacidad efectiva y meses de carga contratada. | G13: Infrautilización inferior al 40 %, o saturación con retrasos acreditados. | H13: Utilización 40–60 %, o saturación con riesgos de plazo. | I13: Utilización 60–75 %. | J13: Utilización 75–90 % con carga contratada a 24 meses. | K13: Utilización 80–95 % con carga contratada superior a 36 meses y margen para absorber picos. | L13: N2 | M13: I01, P06 | N13: Puntuar 0–100 eligiendo el nivel de la rúbrica cuya descripción se cumple con evidencia citada (EVIDENCIA_ID). Valores intermedios solo si la evidencia sitúa a la empresa entre dos niveles; conservar el rango. Sin evidencia suficiente: no puntuar. La saturación no es una fortaleza: una planta al 100 % con retrasos puntúa 0.
... A17: I06 | B17: IND | C17: Integración industrial | D17: 8 | E17: Mayor es mejor | F17: Grado de integración vertical y procesos controlados internamente. | G17: Ensamblador bajo licencia sin control de procesos. | H17: Control de fabricación con diseño y pruebas externos. | I17: Control de fabricación e integración física en planta. | J17: Control de diseño, fabricación e integración. | K17: Control del ciclo industrial completo, incluidas pruebas y aceptación, en varias plantas coordinadas. | L17: N2 | M17: D04 | N17: Puntuar 0–100 eligiendo el nivel de la rúbrica cuya descripción se cumple con evidencia citada (EVIDENCIA_ID). Valores intermedios solo si la evidencia sitúa a la empresa entre dos niveles; conservar el rango. Sin evidencia suficiente: no puntuar. D04 evalúa la integración de sistemas de misión (responsabilidad de arquitectura); I06 evalúa el control del proceso industrial.
A18: I07 | B18: IND | C18: Digitalización industrial | D18: 6 | E18: Mayor es mejor | F18: Ingeniería basada en modelos, gemelo digital, sistemas de ejecución de fabricación, resultados medidos. | G18: Sin evidencia. | H18: Iniciativas piloto. | I18: Sistemas de gestión y diseño digital implantados en la planta principal. | J18: Gemelo digital o ingeniería basada en modelos aplicados en programas en curso. | K18: Fabricación digital integrada en toda la red con resultados medidos y publicados. | L18: N2 | N18: Puntuar 0–100 eligiendo el nivel de la rúbrica cuya descripción se cumple con evidencia citada (EVIDENCIA_ID). Valores intermedios solo si la evidencia sitúa a la empresa entre dos niveles; conservar el rango. Sin evidencia suficiente: no puntuar.
A19: I08 | B19: IND | C19: Inversión industrial | D19: 10 | E19: Mayor es mejor | F19: Capex industrial / cifra de negocio (media de tres ejercicios) comparado con la amortización, y destino de la inversión. | G19: Capex inferior a la amortización de forma sostenida (descapitalización). | H19: Capex similar a la amortización sin proyectos definidos. | I19: Capex superior a la amortización con proyectos definidos. | J19: Plan de inversión plurianual en ejecución ligado a contratos. | K19: Inversiones completadas y operativas que amplían la capacidad demostrada. | L19: N1 | M19: F09 | N19: Puntuar 0–100 eligiendo el nivel de la rúbrica cuya descripción se cumple con evidencia citada (EVIDENCIA_ID). Valores intermedios solo si la evidencia sitúa a la empresa entre dos niveles; conservar el rango. Sin evidencia suficiente: no puntuar.
A20: I09 | B20: IND | C20: Escalabilidad | D20: 8 | E20: Mayor es mejor | F20: Evidencia de aumento de cadencia, turnos, líneas o plantas; limitaciones de suelo, plantilla y proveedores. | G20: Imposible sin nueva planta. | H20: Escalado limitado por suelo, plantilla o proveedores sin plan. | I20: Escalado posible con inversión identificada. | J20: Escalado demostrado parcialmente (turnos, líneas adicionales). | K20: Aumento de cadencia demostrado recientemente o capacidad modular acreditada. | L20: N2 | M20: I01 | N20: Puntuar 0–100 eligiendo el nivel de la rúbrica cuya descripción se cumple con evidencia citada (EVIDENCIA_ID). Valores intermedios solo si la evidencia sitúa a la empresa entre dos niveles; conservar el rango. Sin evidencia suficiente: no puntuar.
A21: I10 | B21: IND | C21: Resiliencia industrial | D21: 8 | E21: Mayor es mejor | F21: Redundancia de plantas y procesos críticos, planes de continuidad probados, certificaciones de seguridad. | G21: Planta única sin plan de continuidad. | H21: Planta única con plan de continuidad. | I21: Varias plantas con dependencias críticas únicas. | J21: Redundancia en procesos críticos y planes probados. | K21: Red redundante, certificaciones de seguridad y continuidad demostrada en un incidente real. | L21: N2 | M21: I05, P09 | N21: Puntuar 0–100 eligiendo el nivel de la rúbrica cuya descripción se cumple con evidencia citada (EVIDENCIA_ID). Valores intermedios solo si la evidencia sitúa a la empresa entre dos niveles; conservar el rango. Sin evidencia suficiente: no puntuar.
A22: D01 | B22: DEF | C22: Programas estratégicos | D22: 12 | E22: Mayor es mejor | F22: Número de programas estratégicos con contrato en vigor y papel desempeñado: contratista principal, socio o suministrador. | G22: Ninguno. | H22: Suministrador de nivel 2 o 3 en uno. | I22: Socio o suministrador principal en uno. | J22: Contratista principal en uno, o socio en varios. | K22: Contratista principal en varios programas estratégicos nacionales o multinacionales con contrato en vigor. | L22: N1 | M22: D11, P04 | N22: Puntuar 0–100 eligiendo el nivel de la rúbrica cuya descripción se cumple con evidencia citada (EVIDENCIA_ID). Valores intermedios solo si la evidencia sitúa a la empresa entre dos niveles; conservar el rango. Sin evidencia suficiente: no puntuar. La calificación de estratégico procede de documentación oficial (ley de programación, presupuesto, PESCO, EDF, acuerdos G2G), no de la empresa.
A23: D02 | B23: DEF | C23: Backlog militar firme | D23: 12 | E23: Mayor es mejor | F23: Porcentaje de la cartera de defensa que es firme contractual frente a opciones, MoU y pipeline; respaldo presupuestario. | G23: Cartera no desglosada, o mayoritariamente MoU y expectativas. | H23: Cartera firme inferior al 50 %. | I23: Cartera firme entre el 50 % y el 75 %. | J23: Cartera firme superior al 75 % con opciones identificadas. | K23: Cartera firme superior al 85 % en contratos plurianuales con financiación presupuestaria aprobada. | L23: N1 | M23: F08, P02 | N23: Puntuar 0–100 eligiendo el nivel de la rúbrica cuya descripción se cumple con evidencia citada (EVIDENCIA_ID). Valores intermedios solo si la evidencia sitúa a la empresa entre dos niveles; conservar el rango. Sin evidencia suficiente: no puntuar. F08 mide años de cobertura y conversión; D02 mide firmeza y composición. El mismo importe de cartera no puede elevar ambos.
A24: D03 | B24: DEF | C24: Sostenimiento y ciclo de vida | D24: 9 | E24: Mayor es mejor | F24: Ingresos de sostenimiento / ingresos de defensa y contratos de apoyo al ciclo de vida en vigor. | G24: Sin actividad de sostenimiento. | H24: Inferior al 10 % de los ingresos de defensa o esporádica. | I24: Entre el 10 % y el 25 % con contratos. | J24: Entre el 25 % y el 40 % con contratos plurianuales. | K24: Superior al 40 %, o autoridad de diseño con contratos de ciclo de vida a largo plazo. | L24: N1 | M24: P04 | N24: Puntuar 0–100 eligiendo el nivel de la rúbrica cuya descripción se cumple con evidencia citada (EVIDENCIA_ID). Valores intermedios solo si la evidencia sitúa a la empresa entre dos niveles; conservar el rango. Sin evidencia suficiente: no puntuar.
A25: D04 | B25: DEF | C25: Integración de sistemas | D25: 10 | E25: Mayor es mejor | F25: Papel acreditado en programas entregados: componente, subsistema, integrador de subsistemas, integrador de plataforma, autoridad de diseño. | G25: Suministrador de componentes. | H25: Responsable de un subsistema. | I25: Integrador de subsistemas en plataforma de tercero. | J25: Integrador de plataforma en un programa entregado. | K25: Integrador de plataforma y sistema de misión en varios programas, con autoridad de diseño. | L25: N1 | M25: I06, D09 | N25: Puntuar 0–100 eligiendo el nivel de la rúbrica cuya descripción se cumple con evidencia citada (EVIDENCIA_ID). Valores intermedios solo si la evidencia sitúa a la empresa entre dos niveles; conservar el rango. Sin evidencia suficiente: no puntuar.
A26: D05 | B26: DEF | C26: Tecnologías críticas | D26: 10 | E26: Mayor es mejor | F26: Número de tecnologías críticas industrializadas y posición relativa (sustituible o de referencia). | G26: Ninguna. | H26: Una, en fase de demostrador. | I26: Una o dos industrializadas. | J26: Varias industrializadas en productos en servicio. | K26: Posición de referencia en varias tecnologías críticas, difícilmente sustituible. | L26: N3 | M26: P08, D09 | N26: Puntuar 0–100 eligiendo el nivel de la rúbrica cuya descripción se cumple con evidencia citada (EVIDENCIA_ID). Valores intermedios solo si la evidencia sitúa a la empresa entre dos niveles; conservar el rango. Sin evidencia suficiente: no puntuar. P08 evalúa tecnologías en desarrollo; D05 solo las industrializadas. La lista de tecnologías críticas se toma de documentos oficiales (EDA, EDF, planes nacionales).
A27: D06 | B27: DEF | C27: Clientes gubernamentales | D27: 8 | E27: Mayor es mejor | F27: Número de gobiernos cliente con contratos en vigor, antigüedad de la relación, acuerdos G2G. | G27: Sin cliente gubernamental directo. | H27: Un cliente con relación reciente. | I27: Cliente doméstico consolidado. | J27: Cliente doméstico y de dos a cuatro gobiernos aliados. | K27: Cartera amplia de gobiernos con contratos recurrentes y acuerdos G2G. | L27: N1 | M27: D07, D12 | N27: Puntuar 0–100 eligiendo el nivel de la rúbrica cuya descripción se cumple con evidencia citada (EVIDENCIA_ID). Valores intermedios solo si la evidencia sitúa a la empresa entre dos niveles; conservar el rango. Sin evidencia suficiente: no puntuar.
A28: D07 | B28: DEF | C28: Exportación de defensa | D28: 8 | E28: Mayor es mejor | F28: Ingresos de defensa de exportación / ingresos de defensa, número de mercados. | G28: Sin exportación. | H28: Inferior al 10 % y esporádica. | I28: Entre el 10 % y el 25 %. | J28: Entre el 25 % y el 50 % en varios mercados. | K28: Superior al 50 % diversificada, o exportación en programas de referencia. | L28: N1 | M28: D06 | N28: Puntuar 0–100 eligiendo el nivel de la rúbrica cuya descripción se cumple con evidencia citada (EVIDENCIA_ID). Valores intermedios solo si la evidencia sitúa a la empresa entre dos niveles; conservar el rango. Sin evidencia suficiente: no puntuar. En mercados domésticos muy grandes (Estados Unidos, China) una baja exportación no indica debilidad: puntuar frente a pares del mismo país y declararlo como ajuste de benchmark.
A29: D08 | B29: DEF | C29: Interoperabilidad y estándares | D29: 6 | E29: Mayor es mejor | F29: Certificaciones STANAG u otras, participación en programas multinacionales con interoperabilidad demostrada. | G29: Sin evidencia. | H29: Cumplimiento parcial. | I29: Productos certificados en estándares relevantes. | J29: Participación en programas multinacionales con interoperabilidad demostrada. | K29: Referencia en estándares y en integración multinacional. | L29: N3 | N29: Puntuar 0–100 eligiendo el nivel de la rúbrica cuya descripción se cumple con evidencia citada (EVIDENCIA_ID). Valores intermedios solo si la evidencia sitúa a la empresa entre dos niveles; conservar el rango. Sin evidencia suficiente: no puntuar. Para empresas fuera de la OTAN, usar los estándares del bloque de referencia del cliente y declararlo.
A30: D09 | B30: DEF | C30: Propiedad intelectual y know-how | D30: 7 | E30: Mayor es mejor | F30: Autoridad de diseño, cartera de patentes, dependencia de licencias de terceros. | G30: Todo bajo licencia de terceros. | H30: IP propia marginal. | I30: IP propia en subsistemas. | J30: Autoridad de diseño en los productos principales. | K30: IP propia en plataforma completa, cartera de patentes y know-how protegido. | L30: N2 | M30: D04, D05 | N30: Puntuar 0–100 eligiendo el nivel de la rúbrica cuya descripción se cumple con evidencia citada (EVIDENCIA_ID). Valores intermedios solo si la evidencia sitúa a la empresa entre dos niveles; conservar el rango. Sin evidencia suficiente: no puntuar.
A31: D10 | B31: DEF | C31: Autonomía, soberanía y control de exportaciones | D31: 8 | E31: Mayor es mejor | F31: Componentes y tecnologías sujetos a control de terceros, exportaciones bloqueadas, sanciones vigentes, participación en programas de soberanía. | G31: Empresa sancionada, o producto principal inviable sin licencia de un tercero que la deniega. | H31: Dependencias de licencia que bloquean exportaciones relevantes. | I31: Dependencias conocidas con alternativas en desarrollo. | J31: Dependencia limitada; productos libres de control de terceros en líneas principales. | K31: Autonomía en tecnologías clave y encaje demostrado en programas de soberanía. | L31: N1 | M31: I05, F10 | N31: Puntuar 0–100 eligiendo el nivel de la rúbrica cuya descripción se cumple con evidencia citada (EVIDENCIA_ID). Valores intermedios solo si la evidencia sitúa a la empresa entre dos niveles; conservar el rango. Sin evidencia suficiente: no puntuar. Nuevo alcance en 2.3: incorpora control de exportaciones y sanciones, que no tenían indicador. Las sanciones se acreditan con listas oficiales (UE, OFAC, ONU, Reino Unido).
A32: D11 | B32: DEF | C32: Pipeline estratégico | D32: 5 | E32: Mayor es mejor | F32: Número de competiciones con oferta presentada, preselección o acuerdo industrial, y calendario oficial. | G32: Ninguna. | H32: Una sin preselección. | I32: Varias con oferta presentada. | J32: Preselección en programas relevantes. | K32: Posición de favorito acreditada en varios programas con calendario oficial. | L32: N3 | M32: D01, P03 | N32: Puntuar 0–100 eligiendo el nivel de la rúbrica cuya descripción se cumple con evidencia citada (EVIDENCIA_ID). Valores intermedios solo si la evidencia sitúa a la empresa entre dos niveles; conservar el rango. Sin evidencia suficiente: no puntuar. P03 mide la cobertura de ingresos a 3–5 años; D11 solo programas identificados públicamente. El tipo de evidencia es EXPECTATIVA salvo preselección documentada.
A33: D12 | B33: DEF | C33: Concentración de programas y clientes | D33: 5 | E33: Menor es mejor | F33: Peso del mayor programa y del mayor cliente en los ingresos de defensa. | G33: Un programa superior al 60 %, o un cliente superior al 80 % sin sustitución prevista. | H33: Mayor programa entre el 40 % y el 60 %. | I33: Mayor programa entre el 25 % y el 40 %. | J33: Mayor programa inferior al 25 % y mayor cliente inferior al 60 %. | K33: Cartera diversificada sin ningún programa superior al 15 %. | L33: N1 | M33: D06, F10, P09 | N33: Puntuar 0–100 eligiendo el nivel de la rúbrica cuya descripción se cumple con evidencia citada (EVIDENCIA_ID). Valores intermedios solo si la evidencia sitúa a la empresa entre dos niveles; conservar el rango. Sin evidencia suficiente: no puntuar. Un cliente doméstico dominante es normal en defensa; pondera más la concentración por programa que por cliente.
A34: P01 | B34: PRO | C34: Crecimiento esperado de ingresos | D34: 12 | E34: Mayor es mejor | F34: Crecimiento anual previsto de la cifra de negocio, según guía corporativa contrastada. | G34: Decrecimiento previsto o guía retirada. | H34: Crecimiento 0–2 %. | I34: Crecimiento 2–6 %. | J34: Crecimiento 6–12 % respaldado por cartera. | K34: Crecimiento superior al 12 % respaldado por cartera firme y presupuestos aprobados. | L34: N2 | M34: P02 | N34: Puntuar 0–100 eligiendo el nivel de la rúbrica cuya descripción se cumple con evidencia citada (EVIDENCIA_ID). Valores intermedios solo si la evidencia sitúa a la empresa entre dos niveles; conservar el rango. Sin evidencia suficiente: no puntuar. Tipo de evidencia: EXPECTATIVA. Identificar siempre quién formula la previsión.
A35: P02 | B35: PRO | C35: Visibilidad 12–24 meses | D35: 14 | E35: Mayor es mejor | F35: Cartera firme ejecutable en el periodo / ingresos previstos en el periodo. | G35: Inferior al 50 %. | H35: Entre el 50 % y el 70 %. | I35: Entre el 70 % y el 85 %. | J35: Entre el 85 % y el 100 %. | K35: Superior al 100 %. | L35: N1 | M35: F08, D02, P01 | N35: Puntuar 0–100 eligiendo el nivel de la rúbrica cuya descripción se cumple con evidencia citada (EVIDENCIA_ID). Valores intermedios solo si la evidencia sitúa a la empresa entre dos niveles; conservar el rango. Sin evidencia suficiente: no puntuar.
A36: P03 | B36: PRO | C36: Visibilidad 3–5 años | D36: 10 | E36: Mayor es mejor | F36: (Cartera firme + opciones) ejecutables en el horizonte / ingresos previstos en el horizonte. | G36: Inferior al 25 %. | H36: Entre el 25 % y el 40 %. | I36: Entre el 40 % y el 60 %. | J36: Entre el 60 % y el 80 %. | K36: Superior al 80 %. | L36: N1 | M36: D11 | N36: Puntuar 0–100 eligiendo el nivel de la rúbrica cuya descripción se cumple con evidencia citada (EVIDENCIA_ID). Valores intermedios solo si la evidencia sitúa a la empresa entre dos niveles; conservar el rango. Sin evidencia suficiente: no puntuar.
A37: P04 | B37: PRO | C37: Visibilidad 5–10 años | D37: 6 | E37: Mayor es mejor | F37: Programas de sostenimiento, acuerdos marco y programas multinacionales en desarrollo con calendario a largo plazo. | G37: Ninguno. | H37: Expectativas sin acuerdos. | I37: Un programa de ciclo largo con contrato. | J37: Varios programas de ciclo largo con contrato. | K37: Varios programas con financiación plurianual aprobada y sostenimiento asociado. | L37: N3 | M37: D01, D03 | N37: Puntuar 0–100 eligiendo el nivel de la rúbrica cuya descripción se cumple con evidencia citada (EVIDENCIA_ID). Valores intermedios solo si la evidencia sitúa a la empresa entre dos niveles; conservar el rango. Sin evidencia suficiente: no puntuar.
A38: P05 | B38: PRO | C38: Conversión a rentabilidad | D38: 14 | E38: Mayor es mejor | F38: Mezcla de contratos (precio fijo frente a coste), fase de los programas (desarrollo frente a serie y sostenimiento), historial de márgenes por fase. | G38: Crecimiento concentrado en desarrollo a precio fijo con historial de sobrecostes. | H38: Mezcla desfavorable. | I38: Mezcla equilibrada. | J38: Paso a fase de serie o sostenimiento con márgenes acreditados. | K38: Mezcla favorable con márgenes crecientes previstos y respaldo contractual. | L38: N2 | M38: F01, I04 | N38: Puntuar 0–100 eligiendo el nivel de la rúbrica cuya descripción se cumple con evidencia citada (EVIDENCIA_ID). Valores intermedios solo si la evidencia sitúa a la empresa entre dos niveles; conservar el rango. Sin evidencia suficiente: no puntuar.
A39: P06 | B39: PRO | C39: Capacidad de ejecución futura | D39: 12 | E39: Mayor es mejor | F39: Brechas identificadas entre el volumen previsto y los recursos disponibles o planificados. | G39: Crecimiento previsto incompatible con la capacidad. | H39: Brechas críticas sin plan. | I39: Brechas con plan financiado parcialmente. | J39: Plan de capacidad financiado y en ejecución. | K39: Capacidad ya disponible o demostrada para el volumen previsto. | L39: N2 | M39: I02, I03 | N39: Puntuar 0–100 eligiendo el nivel de la rúbrica cuya descripción se cumple con evidencia citada (EVIDENCIA_ID). Valores intermedios solo si la evidencia sitúa a la empresa entre dos niveles; conservar el rango. Sin evidencia suficiente: no puntuar.
A40: P07 | B40: PRO | C40: Balance de catalizadores y riesgos | D40: 12 | E40: Mayor es mejor | F40: Número, probabilidad e impacto de catalizadores frente a riesgos en el horizonte 12–36 meses. | G40: Riesgos de alto impacto y alta probabilidad dominan, sin catalizadores. | H40: Predominan los riesgos. | I40: Equilibrio. | J40: Predominan catalizadores con riesgos mitigables. | K40: Catalizadores concretos y datados con riesgos de bajo impacto. | L40: N2 | M40: F10 | N40: Puntuar 0–100 eligiendo el nivel de la rúbrica cuya descripción se cumple con evidencia citada (EVIDENCIA_ID). Valores intermedios solo si la evidencia sitúa a la empresa entre dos niveles; conservar el rango. Sin evidencia suficiente: no puntuar. Sustituye a los antiguos indicadores separados de catalizadores, riesgos prospectivos y señales tempranas. Las señales pasan a la hoja de alerta temprana.
A41: P08 | B41: PRO | C41: Opcionalidad tecnológica | D41: 10 | E41: Mayor es mejor | F41: Demostradores, I+D financiada, patentes recientes, compromisos de cliente sobre tecnologías aún no industrializadas. | G41: Sin I+D relevante. | H41: I+D sin demostradores. | I41: Demostradores en curso. | J41: Demostradores validados con cliente. | K41: Tecnologías en transición a programa con compromiso de cliente. | L41: N3 | M41: D05 | N41: Puntuar 0–100 eligiendo el nivel de la rúbrica cuya descripción se cumple con evidencia citada (EVIDENCIA_ID). Valores intermedios solo si la evidencia sitúa a la empresa entre dos niveles; conservar el rango. Sin evidencia suficiente: no puntuar.
A42: P09 | B42: PRO | C42: Resiliencia estratégica | D42: 10 | E42: Mayor es mejor | F42: Impacto estimado del escenario bajista sobre ingresos, margen y continuidad, y mitigaciones existentes. | G42: El escenario bajista compromete la continuidad. | H42: Impacto severo sin mitigación. | I42: Impacto relevante con mitigación parcial. | J42: Impacto absorbible por diversificación. | K42: Escenario bajista absorbible sin cambio de categoría DCIP. | L42: N2 | M42: D12, I10 | N42: Puntuar 0–100 eligiendo el nivel de la rúbrica cuya descripción se cumple con evidencia citada (EVIDENCIA_ID). Valores intermedios solo si la evidencia sitúa a la empresa entre dos niveles; conservar el rango. Sin evidencia suficiente: no puntuar.

Sheet Reglas
A1: DCIP 2.3 — Matriz de scoring v3.0 — 05/10/2026
A3: REGLA | B3: ESPECIFICACION
A4: Versión | B4: DCIP 2.3 Scoring Matrix v3.0 — 05/10/2026. Sustituye a la v2.01 (48 indicadores).
A5: Estructura | B5: 41 indicadores: FIN 10, IND 10, DEF 12, PRO 9. Cada dimensión suma 100 puntos.
A6: Pesos de dimensión | B6: FIN 25 % · IND 25 % · DEF 25 % · PRO 25 %. Fijos.
A7: Rúbrica | B7: Cinco niveles por indicador: 0 / 25 / 50 / 75 / 100. El nivel se elige por la descripción que la evidencia acredita. 100 es siempre la situación más favorable, también en los indicadores cuya métrica es 'menor es mejor'.
A8: Puntuación intermedia | B8: Permitida solo si la evidencia sitúa a la empresa entre dos niveles; entonces se registra el rango (mínimo y máximo) y el punto central.
A9: Evidencia | B9: Cada puntuación cita uno o varios EVIDENCIA_ID. Sin evidencia suficiente el indicador queda vacío: no se imputa.
A10: Doble conteo | B10: La columna NO_DOBLE_CONTEO lista los indicadores que no pueden puntuarse con el mismo hecho. Un EVIDENCIA_ID no puede sustentar dos indicadores excluyentes.
A11: Normalización | B11: Nota de dimensión = Σ(puntuación × peso) / Σ(pesos con puntuación). Nota prudente = (Σ(puntuación × peso) + 25 × Σ(pesos sin puntuación)) / 100.
A12: Rango | B12: Se publica el intervalo [prudente, normalizada]. Si cruza una banda, la categoría se expresa como rango y no se fuerza una banda única.
A13: Cobertura | B13: Σ pesos con puntuación / 100. ≥ 80 %: concluyente. 60–79 %: con reservas, confianza máxima MEDIA. < 60 %: dimensión NO CONCLUYENTE y sin DCIP global.
A14: Redondeo | B14: Las notas de dimensión y el DCIP se redondean al entero más próximo (mitad hacia arriba) antes de aplicar bandas.
... A28: Sanciones y control de exportaciones | B28: Se evalúan en D10 con listas oficiales (UE, OFAC, ONU, Reino Unido). Su efecto financiero cuantificado va a F10.

Sheet Control
A1: Control de integridad de la matriz
A2: Fórmulas sobre la hoja Matriz_v3. Todas las sumas deben ser 100 y el total de indicadores igual al declarado.
A3: DIMENSION | B3: SUMA_PESOS | C3: INDICADORES | D3: CONTROL
A4: FIN | B4: =SUMIF(Matriz_v3!$B$2:$B$42,A4,Matriz_v3!$D$2:$D$42) -> 100 | C4: =COUNTIF(Matriz_v3!$B$2:$B$42,A4) -> 10 | D4: =IF(B4=100,"OK","ERROR") -> OK
A5: IND | B5: =SUMIF(Matriz_v3!$B$2:$B$42,A5,Matriz_v3!$D$2:$D$42) -> 100 | C5: =COUNTIF(Matriz_v3!$B$2:$B$42,A5) -> 10 | D5: =IF(B5=100,"OK","ERROR") -> OK
A6: DEF | B6: =SUMIF(Matriz_v3!$B$2:$B$42,A6,Matriz_v3!$D$2:$D$42) -> 100 | C6: =COUNTIF(Matriz_v3!$B$2:$B$42,A6) -> 12 | D6: =IF(B6=100,"OK","ERROR") -> OK
A7: PRO | B7: =SUMIF(Matriz_v3!$B$2:$B$42,A7,Matriz_v3!$D$2:$D$42) -> 100 | C7: =COUNTIF(Matriz_v3!$B$2:$B$42,A7) -> 9 | D7: =IF(B7=100,"OK","ERROR") -> OK
A8: TOTAL | B8: =SUM(B4:B7) -> 400 | C8: =SUM(C4:C7) -> 41 | D8: =IF(AND(B8=400,C8=41),"OK","ERROR") -> OK
A10: IDs únicos | B10: =IF(SUMPRODUCT(1/COUNTIF(Matriz_v3!$A$2:$A$42,Matriz_v3!$A$2:$A$42))=41,"OK","DUPLICADOS") -> OK

Sheet Confianza
A1: Nivel de fuente → confianza máxima; antigüedad → penalización; cobertura → límite
A3: NIVEL | B3: DENOMINACION | C3: DESCRIPCION | D3: CONFIANZA_MAX
A4: N1 | B4: Primaria auditada / oficial | C4: Cuentas anuales auditadas; informes financieros regulados; registros mercantiles y de propiedad; contratos y adjudicaciones publicados por el órgano contratante; presupuestos y documentación oficial del Estado. | D4: MUY ALTA
A5: N2 | B5: Primaria corporativa | C5: Informes anuales e integrados; presentaciones a inversores; comunicados de la empresa; documentación técnica propia; web corporativa. | D5: ALTA
A6: N3 | B6: Institucional / supranacional | C6: UE, EDA, OCCAR, NSPA, OTAN, bancos centrales, oficinas de auditoría pública, agencias de adquisición nacionales, programas públicos de I+D. | D6: ALTA
A7: N4 | B7: Sectorial especializada | C7: SIPRI, IISS, asociaciones industriales (ASD, AIAD, TEDAE, BDSV, GIFAS, NDIA), bases de datos sectoriales y estudios técnicos reconocidos. | D7: MEDIA
A8: N5 | B8: Prensa económica y de defensa | C8: Prensa generalista y especializada. Útil para contexto y cronología; toda afirmación material debe contrastarse con N1 a N3. | D8: BAJA
A9: N6 | B9: Otras fuentes | C9: Blogs, foros, redes sociales, fuentes anónimas, informes no firmados. Nunca fundamento único de una afirmación crítica. | D9: MUY BAJA
B11: ANTIGÜEDAD RESPECTO A LA FECHA DE CORTE | D11: PENALIZACION (niveles)
B12: ≤ 12 meses (≤ 18 si son cuentas anuales auditadas) | D12: 0
B13: 12–24 meses (18–30 si son cuentas anuales auditadas) | D13: -1
B14: > 24 meses (> 30 si son cuentas anuales auditadas) | D14: -2
B16: COBERTURA DE LA DIMENSION | C16: EFECTO
B17: ≥ 80 % | C17: Dimensión concluyente. Puede alcanzar confianza ALTA o MUY ALTA.
B18: 60–79 % | C18: Dimensión concluyente con reservas. Confianza máxima MEDIA. Se publica el rango prudente–normalizado.
B19: < 60 % | C19: Dimensión NO CONCLUYENTE. No se calcula la nota de la dimensión ni el DCIP global; se publica el detalle disponible.

Sheet Bandas_y_escalas
A1: Bandas DCIP y escalas de juicio
A3: BANDA | B3: MIN | C3: MAX | D3: USO
A4: Crítica | B4: 0 | C4: 20 | D4: Aplicar sobre la nota entera. Si el rango prudente–normalizado cruza esta banda, publicar el rango.
A5: Débil | B5: 21 | C5: 40 | D5: Aplicar sobre la nota entera. Si el rango prudente–normalizado cruza esta banda, publicar el rango.
A6: Estable | B6: 41 | C6: 60 | D6: Aplicar sobre la nota entera. Si el rango prudente–normalizado cruza esta banda, publicar el rango.
A7: Favorable | B7: 61 | C7: 80 | D7: Aplicar sobre la nota entera. Si el rango prudente–normalizado cruza esta banda, publicar el rango.
A8: Muy favorable | B8: 81 | C8: 100 | D8: Aplicar sobre la nota entera. Si el rango prudente–normalizado cruza esta banda, publicar el rango.
A10: ESTADO EMPRESARIAL | D10: DESCRIPCION
A11: CRÍTICO | D11: Continuidad comprometida: patrimonio, liquidez o capacidad industrial en situación de riesgo inmediato.
A12: FRÁGIL | D12: Opera con dependencias relevantes (apoyo público, un programa, un cliente) y márgenes de maniobra reducidos.
A13: ESTABLE | D13: Situación económica e industrial sostenible sin tensiones materiales, con debilidades identificadas.
A14: SÓLIDO | D14: Finanzas saneadas y capacidad industrial demostrada, con ejecución acreditada.
A15: MUY SÓLIDO | D15: Posición financiera e industrial de referencia, con resiliencia demostrada ante escenarios adversos.
A17: ATRACTIVIDAD ESTRATEGICA | D17: DESCRIPCION
A18: BAJA | D18: Sin papel relevante en capacidades, programas o tecnologías de defensa.
A19: MODERADA | D19: Suministrador sustituible en programas de interés limitado.
A20: RELEVANTE | D20: Participación en programas o tecnologías de interés para la soberanía o la política industrial.
A21: ALTA | D21: Integrador o tecnólogo de referencia en programas estratégicos con cartera firme.
A22: MUY ALTA | D22: Actor difícilmente sustituible en capacidades críticas, con proyección a largo plazo.

Sheet Mapeo_2.2_a_2.3
A1: DIM | B1: INDICADOR 2.2 | C1: PESO 2.2 | D1: DESTINO 2.3 | E1: PESO 2.3 | F1: CAMBIO
A2: FIN | B2: Rentabilidad operativa | C2: 12 | D2: F01 | E2: 14 | F2: Mantenido; rúbrica con anclas de margen EBIT
A3: FIN | B3: Evolución de rentabilidad | C3: 8 | D3: F02 | E3: 8 | F3: Mantenido; horizonte fijado en tres ejercicios
A4: FIN | B4: Flujo de caja operativo | C4: 10 | D4: F03 | E4: 12 | F4: Mantenido; métrica FCO/EBITDA
A5: FIN | B5: Liquidez | C5: 8 | D5: F04 | E5: 8 | F5: Mantenido; ratio corriente y cobertura de vencimientos
A6: FIN | B6: Endeudamiento financiero | C6: 8 | D6: F05 | E6: 10 | F6: Mantenido; deuda neta/EBITDA con tratamiento IFRS 16
A7: FIN | B7: Patrimonio y solvencia | C7: 10 | D7: F06 | E7: 10 | F7: Mantenido; patrimonio/activo
A8: FIN | B8: Dependencia de apoyo público | C8: 8 | D8: F07 | E8: 8 | F8: Mantenido; redefinido como dependencia financiera, no propiedad
A9: FIN | B9: Calidad de cartera | C9: 10 | D9: F08 | E9: 14 | F9: Fusionado con Conversión cartera→ingresos
A10: FIN | B10: Conversión cartera→ingresos | C10: 8 | D10: F08 | F10: Fusionado en F08
A11: FIN | B11: Disciplina de capital | C11: 8 | D11: F09 | E11: 8 | F11: Mantenido
A12: FIN | B12: Riesgo extraordinario | C12: 6 | D12: F10 | E12: 8 | F12: Mantenido; efecto financiero de sanciones separado hacia D10
A13: FIN | B13: Transparencia financiera | C13: 4 | D13: — | F13: Eliminado: es un atributo de la evidencia y ya está en la confianza
A14: IND | B14: Capacidad instalada | C14: 10 | D14: I01 | E14: 18 | F14: Fusionado en Capacidad industrial (cadena instalada→efectiva→demostrada)
A15: IND | B15: Capacidad efectiva | C15: 10 | D15: I01 | F15: Fusionado en I01
A16: IND | B16: Capacidad demostrada | C16: 10 | D16: I01 | F16: Fusionado en I01
A17: IND | B17: Carga y utilización | C17: 8 | D17: I02 | E17: 10 | F17: Mantenido; óptimo intermedio explícito
A18: IND | B18: Plantilla y cualificación | C18: 8 | D18: I03 | E18: 10 | F18: Mantenido
A19: IND | B19: Productividad/ejecución | C19: 10 | D19: I04 | E19: 12 | F19: Mantenido; evidencia del cliente prioritaria
A20: IND | B20: Cadena de suministro | C20: 8 | D20: I05 | E20: 10 | F20: Mantenido; dependencia regulatoria separada hacia D10
A21: IND | B21: Integración industrial | C21: 8 | D21: I06 | E21: 8 | F21: Mantenido; delimitado frente a D04
A22: IND | B22: Digitalización industrial | C22: 6 | D22: I07 | E22: 6 | F22: Mantenido
A23: IND | B23: Inversión industrial | C23: 8 | D23: I08 | E23: 10 | F23: Mantenido; capex frente a amortización
A24: IND | B24: Escalabilidad | C24: 7 | D24: I09 | E24: 8 | F24: Mantenido
A25: IND | B25: Resiliencia industrial | C25: 7 | D25: I10 | E25: 8 | F25: Mantenido
A26: DEF | B26: Programas estratégicos | C26: 12 | D26: D01 | E26: 12 | F26: Mantenido; calificación por documentación oficial
A27: DEF | B27: Backlog militar firme | C27: 12 | D27: D02 | E27: 12 | F27: Mantenido; redefinido como composición y firmeza
A28: DEF | B28: Sostenimiento/ciclo de vida | C28: 9 | D28: D03 | E28: 9 | F28: Mantenido
... A44: PRO | B44: Catalizadores | C44: 8 | D44: P07 | E44: 12 | F44: Fusionado en Balance de catalizadores y riesgos
A45: PRO | B45: Riesgos prospectivos | C45: 10 | D45: P07 | F45: Fusionado en P07
A46: PRO | B46: Señales tempranas | C46: 5 | D46: — | F46: Eliminado como indicador; pasa a la hoja de alerta temprana
A47: PRO | B47: Opcionalidad tecnológica | C47: 8 | D47: P08 | E47: 10 | F47: Mantenido; delimitado frente a D05
A48: PRO | B48: Resiliencia estratégica | C48: 7 | D48: P09 | E48: 10 | F48: Mantenido
A49: PRO | B49: Calidad de la tesis | C49: 5 | D49: — | F49: Eliminado: califica al analista, no a la empresa; pasa al control 15 de auditoría
B51: Control de pesos 2.2 por dimensión
A52: FIN | C52: =SUMIF($A$2:$A$49,A52,$C$2:$C$49) -> 100 | E52: =SUMIF($A$2:$A$49,A52,$E$2:$E$49) -> 100 | F52: =IF(AND(C52=100,E52=100),"OK","ERROR") -> OK
A53: IND | C53: =SUMIF($A$2:$A$49,A53,$C$2:$C$49) -> 100 | E53: =SUMIF($A$2:$A$49,A53,$E$2:$E$49) -> 100 | F53: =IF(AND(C53=100,E53=100),"OK","ERROR") -> OK
A54: DEF | C54: =SUMIF($A$2:$A$49,A54,$C$2:$C$49) -> 100 | E54: =SUMIF($A$2:$A$49,A54,$E$2:$E$49) -> 100 | F54: =IF(AND(C54=100,E54=100),"OK","ERROR") -> OK
A55: PRO | C55: =SUMIF($A$2:$A$49,A55,$C$2:$C$49) -> 100 | E55: =SUMIF($A$2:$A$49,A55,$E$2:$E$49) -> 100 | F55: =IF(AND(C55=100,E55=100),"OK","ERROR") -> OK
